query_farm_duckdb_json_serialization/__init__.py
query_farm_duckdb_json_serialization/expression.py
query_farm_duckdb_json_serialization/test_expression.py
query_farm_duckdb_json_serialization/value.py
query_farm_duckdb_json_serialization-0.1.4.dist-info/METADATA
query_farm_duckdb_json_serialization-0.1.4.dist-info/WHEEL
query_farm_duckdb_json_serialization-0.1.4.dist-info/licenses/LICENSE
query_farm_duckdb_json_serialization-0.1.4.dist-info/RECORD
