Metadata-Version: 2.3
Name: query-farm-duckdb-json-serialization
Version: 0.1.4
Summary: Integrate with DuckDB's JSON serialization of expressions and values
Project-URL: Repository, https://github.com/query-farm/python-duckdb-json-serilization.git
Project-URL: Issues, https://github.com/query-farm/python-duckdb-json-serialization/issues
Author-email: Rusty Conover <rusty@query.farm>
License: MIT
Keywords: airport,arrow,arrow flight,duckdb,duckdb airport,flight,predicate pushdown,predicates,sql,sql parsing
Classifier: Development Status :: 4 - Beta
Classifier: Intended Audience :: Developers
Classifier: Programming Language :: Python :: 3.11
Classifier: Topic :: Database
Classifier: Topic :: Database :: Database Engines/Servers
Requires-Python: >=3.11
Requires-Dist: pydantic>=2.11.7
